<?xml version="1.0" encoding="utf-8"?>
<method xmlns:xsd="http://www.w3.org/2001/XMLSchema" xmlns:xsi="http://www.w3.org/2001/XMLSchema-instance" name="emulation_lacp_control" name_robot="Emulation Lacp Control" displayPriority="1" ixHalOrProtocolPythonApiSupport="false" ixHalOrProtocolPythonScriptgenSupport="false" ixHalOrProtocolPerlApiSupport="false" ixHalOrProtocolPerlScriptgenSupport="false" ixHalOrProtocolTclApiSupport="false" ixHalOrProtocolTclScriptgenSupport="false" ixLoadPythonApiSupport="false" ixLoadPythonScriptgenSupport="false" ixLoadPerlApiSupport="false" ixLoadPerlScriptgenSupport="false" ixLoadTclApiSupport="false" ixLoadTclScriptgenSupport="false" ixNetworkCpfPythonApiSupport="true" ixNetworkCpfPythonScriptgenSupport="false" ixNetworkCpfPerlApiSupport="true" ixNetworkCpfPerlScriptgenSupport="false" ixNetworkCpfTclApiSupport="true" ixNetworkCpfTclScriptgenSupport="false" ixNetworkCpfRobotApiSupport="true" ixNetworkCpfRobotScriptgenSupport="false" ixNetworkPythonApiSupport="false" ixNetworkPythonScriptgenSupport="false" ixNetworkPerlApiSupport="false" ixNetworkPerlScriptgenSupport="false" ixNetworkTclApiSupport="false" ixNetworkTclScriptgenSupport="false" ixNetworkRobotApiSupport="false" ixNetworkRobotScriptgenSupport="false" Lang="none">
  <description supportType="ixNetworkSupport" contentType="noContent" target="noTarget" />
  <description supportType="ixLoadSupport" contentType="noContent" target="noTarget" />
  <description supportType="ixHalOrProtocolSupport" contentType="noContent" target="noTarget" />
  <description supportType="ixNetworkCpfSupport" contentType="new" target="noTarget">Control Operation on the LACP/Static LAG Protocol
   The following operations are done: 
   1. Restart 
   2. Send Marker Request
   3. Start
   4. Start PDU
   5. Stop
   6. Stop PDU</description>
  <arguments>
    <argument name="mode" definedBy="ciscoDefined" ixHalOrProtocolPythonApiSupport="false" ixHalOrProtocolPythonScriptgenSupport="false" ixHalOrProtocolPerlApiSupport="false" ixHalOrProtocolPerlScriptgenSupport="false" ixHalOrProtocolTclApiSupport="false" ixHalOrProtocolTclScriptgenSupport="false" ixLoadPythonApiSupport="false" ixLoadPythonScriptgenSupport="false" ixLoadPerlApiSupport="false" ixLoadPerlScriptgenSupport="false" ixLoadTclApiSupport="false" ixLoadTclScriptgenSupport="false" ixNetworkCpfPythonApiSupport="true" ixNetworkCpfPythonScriptgenSupport="true" ixNetworkCpfPerlApiSupport="true" ixNetworkCpfPerlScriptgenSupport="true" ixNetworkCpfTclApiSupport="true" ixNetworkCpfTclScriptgenSupport="true" ixNetworkCpfRobotApiSupport="true" ixNetworkCpfRobotScriptgenSupport="true" ixNetworkPythonApiSupport="false" ixNetworkPythonScriptgenSupport="false" ixNetworkPerlApiSupport="false" ixNetworkPerlScriptgenSupport="false" ixNetworkTclApiSupport="false" ixNetworkTclScriptgenSupport="false" ixNetworkRobotApiSupport="false" ixNetworkRobotScriptgenSupport="false" lang="false">
      <ixHalOrProtocolSupport contentType="noContent" target="noTarget" mandatory="false" />
      <ixNetworkSupport contentType="noContent" target="noTarget" mandatory="false" />
      <ixNetworkCpfSupport contentType="new" target="noTarget" mandatory="true">
        <description>
          <text>What is being done to the protocol.  Valid choices are:
    restart - Restart the protocol.
    start   - Start the protocol.
    stop    - Stop the protocol.
    start_pdu    - start_pdu the protocol.
    stop_pdu    - stop_pdu the protocol.
    send_marker_req    - send_marker_req the protocol.</text>
          <choices>
            <choice>
              <choiceName>restart</choiceName>
              <choiceText>Restart the protocol.</choiceText>
            </choice>
            <choice>
              <choiceName>send_marker_req</choiceName>
              <choiceText>send marker req.</choiceText>
            </choice>
            <choice>
              <choiceName>start</choiceName>
              <choiceText>Start the protocol.</choiceText>
            </choice>
            <choice>
              <choiceName>restart_down</choiceName>
              <choiceText>restart the down sessions</choiceText>
            </choice>
            <choice>
              <choiceName>start_pdu</choiceName>
              <choiceText>Start PDU.</choiceText>
            </choice>
            <choice>
              <choiceName>stop</choiceName>
              <choiceText>Stop the protocol.</choiceText>
            </choice>
            <choice>
              <choiceName>stop_pdu</choiceName>
              <choiceText>Stop PDU.</choiceText>
            </choice>
            <choice>
              <choiceName>abort</choiceName>
              <choiceText>Abort.</choiceText>
            </choice>
          </choices>
        </description>
        <restriction type="VALUETYPE" valueType="CHOICES" value="restart send_marker_req start restart_down start_pdu stop stop_pdu abort" />
      </ixNetworkCpfSupport>
      <ixLoadSupport contentType="noContent" target="noTarget" mandatory="false" />
    </argument>
    <argument name="port_handle" definedBy="ciscoDefined" ixHalOrProtocolPythonApiSupport="false" ixHalOrProtocolPythonScriptgenSupport="false" ixHalOrProtocolPerlApiSupport="false" ixHalOrProtocolPerlScriptgenSupport="false" ixHalOrProtocolTclApiSupport="false" ixHalOrProtocolTclScriptgenSupport="false" ixLoadPythonApiSupport="false" ixLoadPythonScriptgenSupport="false" ixLoadPerlApiSupport="false" ixLoadPerlScriptgenSupport="false" ixLoadTclApiSupport="false" ixLoadTclScriptgenSupport="false" ixNetworkCpfPythonApiSupport="true" ixNetworkCpfPythonScriptgenSupport="supportedInOtherCommand" ixNetworkCpfPerlApiSupport="true" ixNetworkCpfPerlScriptgenSupport="supportedInOtherCommand" ixNetworkCpfTclApiSupport="true" ixNetworkCpfTclScriptgenSupport="supportedInOtherCommand" ixNetworkCpfRobotApiSupport="true" ixNetworkCpfRobotScriptgenSupport="supportedInOtherCommand" ixNetworkPythonApiSupport="false" ixNetworkPythonScriptgenSupport="false" ixNetworkPerlApiSupport="false" ixNetworkPerlScriptgenSupport="false" ixNetworkTclApiSupport="false" ixNetworkTclScriptgenSupport="false" ixNetworkRobotApiSupport="false" ixNetworkRobotScriptgenSupport="false" lang="false">
      <ixHalOrProtocolSupport contentType="noContent" target="noTarget" mandatory="false" />
      <ixNetworkSupport contentType="noContent" target="noTarget" mandatory="false" />
      <ixNetworkCpfSupport contentType="new" target="noTarget" mandatory="false">
        <description>
          <text>The port on which to perform action.</text>
        </description>
        <restriction type="VALUETYPE" valueType="REGEXP" value="^[0-9]+/[0-9]+/[0-9]+$" />
      </ixNetworkCpfSupport>
      <ixLoadSupport contentType="noContent" target="noTarget" mandatory="false" />
    </argument>
    <argument name="handle" definedBy="ciscoDefined" ixHalOrProtocolPythonApiSupport="false" ixHalOrProtocolPythonScriptgenSupport="false" ixHalOrProtocolPerlApiSupport="false" ixHalOrProtocolPerlScriptgenSupport="false" ixHalOrProtocolTclApiSupport="false" ixHalOrProtocolTclScriptgenSupport="false" ixLoadPythonApiSupport="false" ixLoadPythonScriptgenSupport="false" ixLoadPerlApiSupport="false" ixLoadPerlScriptgenSupport="false" ixLoadTclApiSupport="false" ixLoadTclScriptgenSupport="false" ixNetworkCpfPythonApiSupport="true" ixNetworkCpfPythonScriptgenSupport="supportedInOtherCommand" ixNetworkCpfPerlApiSupport="true" ixNetworkCpfPerlScriptgenSupport="supportedInOtherCommand" ixNetworkCpfTclApiSupport="true" ixNetworkCpfTclScriptgenSupport="supportedInOtherCommand" ixNetworkCpfRobotApiSupport="true" ixNetworkCpfRobotScriptgenSupport="supportedInOtherCommand" ixNetworkPythonApiSupport="false" ixNetworkPythonScriptgenSupport="false" ixNetworkPerlApiSupport="false" ixNetworkPerlScriptgenSupport="false" ixNetworkTclApiSupport="false" ixNetworkTclScriptgenSupport="false" ixNetworkRobotApiSupport="false" ixNetworkRobotScriptgenSupport="false" lang="false">
      <ixHalOrProtocolSupport contentType="noContent" target="noTarget" mandatory="false" />
      <ixNetworkSupport contentType="noContent" target="noTarget" mandatory="false" />
      <ixNetworkCpfSupport contentType="new" target="noTarget" mandatory="false">
        <description>
          <text />
        </description>
        <restriction type="VALUETYPE" valueType="ANY" />
      </ixNetworkCpfSupport>
      <ixLoadSupport contentType="noContent" target="noTarget" mandatory="false" />
    </argument>
    <argument name="session_type" definedBy="ciscoDefined" ixHalOrProtocolPythonApiSupport="false" ixHalOrProtocolPythonScriptgenSupport="false" ixHalOrProtocolPerlApiSupport="false" ixHalOrProtocolPerlScriptgenSupport="false" ixHalOrProtocolTclApiSupport="false" ixHalOrProtocolTclScriptgenSupport="false" ixLoadPythonApiSupport="false" ixLoadPythonScriptgenSupport="false" ixLoadPerlApiSupport="false" ixLoadPerlScriptgenSupport="false" ixLoadTclApiSupport="false" ixLoadTclScriptgenSupport="false" ixNetworkCpfPythonApiSupport="true" ixNetworkCpfPythonScriptgenSupport="supportedInOtherCommand" ixNetworkCpfPerlApiSupport="true" ixNetworkCpfPerlScriptgenSupport="supportedInOtherCommand" ixNetworkCpfTclApiSupport="true" ixNetworkCpfTclScriptgenSupport="supportedInOtherCommand" ixNetworkCpfRobotApiSupport="true" ixNetworkCpfRobotScriptgenSupport="supportedInOtherCommand" ixNetworkPythonApiSupport="false" ixNetworkPythonScriptgenSupport="false" ixNetworkPerlApiSupport="false" ixNetworkPerlScriptgenSupport="false" ixNetworkTclApiSupport="false" ixNetworkTclScriptgenSupport="false" ixNetworkRobotApiSupport="false" ixNetworkRobotScriptgenSupport="false" lang="false">
      <ixHalOrProtocolSupport contentType="noContent" target="noTarget" mandatory="false" />
      <ixNetworkSupport contentType="noContent" target="noTarget" mandatory="false" />
      <ixNetworkCpfSupport contentType="new" target="noTarget" mandatory="false">
        <description>
          <text>The LACP to be emulated. CHOICES: lacp staticLag.</text>
          <choices>
            <choice>
              <choiceName>lacp</choiceName>
              <choiceText />
            </choice>
            <choice>
              <choiceName>staticLag</choiceName>
              <choiceText />
            </choice>
          </choices>
        </description>
        <restriction type="VALUETYPE" valueType="CHOICES" value="lacp staticLag" />
        <restriction type="DEFAULT" valueType="ANY" value="lacp" />
      </ixNetworkCpfSupport>
      <ixLoadSupport contentType="noContent" target="noTarget" mandatory="false" />
    </argument>
  </arguments>
  <returnValues>
    <returnValue definedBy="ciscoDefined" supportType="ixNetworkCpfSupport">
      <key>status</key>
      <value>$::SUCCESS | $::FAILURE</value>
      <tag value="" />
    </returnValue>
    <returnValue definedBy="ciscoDefined" supportType="ixNetworkCpfSupport">
      <key>log</key>
      <value>If status is failure, detailed information provided.</value>
      <tag value="" />
    </returnValue>
  </returnValues>
  <sampleInput>
    <sampleInputElem supportType="ixNetworkCpfSupport" />
  </sampleInput>
  <sampleOutput>
    <sampleOutputElem supportType="ixNetworkCpfSupport" />
  </sampleOutput>
  <notes>
    <note supportType="ixNetworkCpfSupport"> </note>
  </notes>
  <seeAlso>
    <seeAlsoElem supportType="ixNetworkCpfSupport" />
  </seeAlso>
  <examples>
    <example supportType="ixNetworkCpfSupport" />
  </examples>
  <code_examples />
</method>